LICENSE
MANIFEST.in
README.rst
setup.py
team_password_cli/__init__.py
team_password_cli/__main__.py
team_password_cli/cli.py
team_password_cli/rest_client.py
team_password_cli.egg-info/PKG-INFO
team_password_cli.egg-info/SOURCES.txt
team_password_cli.egg-info/dependency_links.txt
team_password_cli.egg-info/entry_points.txt
team_password_cli.egg-info/not-zip-safe
team_password_cli.egg-info/requires.txt
team_password_cli.egg-info/top_level.txt
tests/__init__.py
tests/test_true.py