Metadata-Version: 1.1
Name: team-password-cli
Version: 1.0.1
Summary: Team Password Manager cli
Home-page: https://github.com/nrocco/team_password_cli
Author: Nico Di Rocco
Author-email: dirocco.nico@gmail.com
License: GPLv3
Download-URL: https://github.com/nrocco/team_password_cli/tags
Platform: UNKNOWN
Classifier: Development Status :: 5 - Production/Stable
Classifier: Environment :: Console
Classifier: License :: OSI Approved :: GNU General Public License v3 (GPLv3)
Classifier: Operating System :: Unix
Classifier: Programming Language :: Python
Classifier: Programming Language :: Python :: 2
Classifier: Programming Language :: Python :: 2.7
Classifier: Programming Language :: Python :: 3
Classifier: Programming Language :: Python :: 3.2
Classifier: Programming Language :: Python :: 3.3
Classifier: Programming Language :: Python :: 3.4
Classifier: Programming Language :: Python :: 3.5
Classifier: Programming Language :: Python :: 3.6
Classifier: Topic :: Software Development :: Libraries :: Python Modules
Classifier: Topic :: Utilities
